utilidades/__init__.py
utilidades/utilidades.py
utilidades_12-1.2.data/scripts/utilidades.py
utilidades_12-1.2.dist-info/LICENSE
utilidades_12-1.2.dist-info/METADATA
utilidades_12-1.2.dist-info/WHEEL
utilidades_12-1.2.dist-info/top_level.txt
utilidades_12-1.2.dist-info/RECORD
