Metadata-Version: 2.1
Name: utilidades-12
Version: 1.2
Summary: several usefull common functions
Home-page: https://github.com/
Author: Thiago Henrique Martinelli
Author-email: thiago.henrique.martinelli@gmail.com
License: UNKNOWN
Platform: UNKNOWN
Classifier: Programming Language :: Python :: 3
Classifier: License :: OSI Approved :: MIT License
Classifier: Operating System :: OS Independent
